{
  "db_name": "PostgreSQL",
  "query": "INSERT INTO technical_seminars (name, timestamp, active, approved)\n                VALUES ($1, $2, $3, $4) RETURNING id",
  "describe": {
    "columns": [
      {
        "ordinal": 0,
        "name": "id",
        "type_info": "Int4"
      }
    ],
    "parameters": {
      "Left": [
        "Varchar",
        "Timestamp",
        "Bool",
        "Bool"
      ]
    },
    "nullable": [
      false
    ]
  },
  "hash": "9b649d19ec5cbb3ec34afca7cf4c3bc31fc9572ba7383af0ec9ed67434e35e62"
}
